pytest_playwright_visual_snapshot/__init__.py
pytest_playwright_visual_snapshot/plugin.py
pytest_playwright_visual_snapshot-0.2.4.dist-info/METADATA
pytest_playwright_visual_snapshot-0.2.4.dist-info/WHEEL
pytest_playwright_visual_snapshot-0.2.4.dist-info/entry_points.txt
pytest_playwright_visual_snapshot-0.2.4.dist-info/RECORD
