Metadata-Version: 2.4
Name: pytest-playwright-visual-snapshot
Version: 0.2.4
Summary: Easy pytest visual regression testing using playwright
Project-URL: Repository, https://github.com/iloveitaly/pytest-playwright-visual-snapshot
Author-email: Michael Bianco <mike@mikebian.co>
Keywords: playwright,pytest,regression,testing,visual
Requires-Python: >=3.10
Requires-Dist: pillow>=11.1.0
Requires-Dist: pixelmatch>=0.3.0
Requires-Dist: pytest-playwright>=0.7.0
